{
  "project_info": {
    "project_number": "1068966136010",
    "firebase_url": "https://ultimate-warrior-fc64a-default-rtdb.firebaseio.com",
    "project_id": "ultimate-warrior-fc64a",
    "storage_bucket": "ultimate-warrior-fc64a.firebasestorage.app"
  },
  "client": [
    {
      "client_info": {
        "mobilesdk_app_id": "1:1068966136010:ios:c8fdb90a5be5eed3944c33",
        "android_client_info": {
          "package_name": "com.LegendaryItem.UltimateWarrior"
        }
      },
      "api_key": [
        {
          "current_key": "AIzaSyCMHiYpdxL8ctqsCmwULtNxx9-wYDhbU98"
        }
      ],
      "services": {
        "analytics_service": {
          "status": 0
        },
        "appinvite_service": {
          "status": 1
        }
      },
      "oauth_client": [
        {
          "client_id": "1068966136010-33o2c3n28l6d8ql0r8amkh60p8o84sca.apps.googleusercontent.com"
        }
      ]
    }
  ],
  "configuration_version": "1"
}